{
  "code": "HT",
  "name": "Haiti",
  "cities": {
    "Ouest": {
      "plane": [],
      "train": [],
      "bus": []
    },
    "Artibonite": {
      "plane": [
        {
          "code": "PAP",
          "name": "Toussaint Louverture International Airport",
          "lat": 18.580023,
          "lng": -72.292596
        }
      ],
      "train": [],
      "bus": []
    },
    "Nord": {
      "plane": [],
      "train": [],
      "bus": []
    },
    "Nord-Ouest": {
      "plane": [
        {
          "code": "JEE",
          "name": "Jérémie Airport",
          "lat": 18.663099,
          "lng": -74.170303
        }
      ],
      "train": [],
      "bus": []
    },
    "Sud-Est": {
      "plane": [
        {
          "code": "CYA",
          "name": "Antoine-Simon International Airport",
          "lat": 18.271099,
          "lng": -73.7883
        }
      ],
      "train": [],
      "bus": []
    },
    "Sud": {
      "plane": [],
      "train": [],
      "bus": []
    },
    "Centre": {
      "plane": [
        {
          "code": "CAP",
          "name": "Cap Haitien International Airport",
          "lat": 19.726734,
          "lng": -72.199576
        }
      ],
      "train": [],
      "bus": []
    },
    "Nippes": {
      "plane": [],
      "train": [],
      "bus": []
    },
    "Grand’Anse": {
      "plane": [],
      "train": [],
      "bus": []
    },
    "Nord-Est": {
      "plane": [],
      "train": [],
      "bus": []
    }
  },
  "meta": {
    "source": {
      "airports": "OurAirports (airports.csv, filtered: scheduled_service=yes, civil)",
      "train": "OpenStreetMap (railway=station/public_transport=station train=yes)",
      "bus": "OpenStreetMap (amenity=bus_station/public_transport=station bus=yes)"
    },
    "generatedAt": "2025-09-02T08:40:13.306Z"
  }
}