{
  "code": "TL",
  "name": "Timor-Leste",
  "cities": {
    "Díli": {
      "plane": [
        {
          "code": "DIL",
          "name": "Presidente Nicolau Lobato International Airport",
          "lat": -8.546562,
          "lng": 125.524507
        }
      ],
      "train": [],
      "bus": [
        {
          "code": "OSM:10939029571",
          "name": "Bis to Dili",
          "lat": -8.5079254,
          "lng": 126.9871062
        }
      ]
    },
    "Bobonaro": {
      "plane": [],
      "train": [],
      "bus": [
        {
          "code": "OSM:5821620453",
          "name": "Bus station to Maubisse",
          "lat": -8.5684125,
          "lng": 125.5939734
        }
      ]
    },
    "Baucau": {
      "plane": [],
      "train": [],
      "bus": [
        {
          "code": "OSM:435803406",
          "name": "Baucau bus station",
          "lat": -8.483698,
          "lng": 126.4529863
        }
      ]
    },
    "Manatuto": {
      "plane": [],
      "train": [],
      "bus": []
    },
    "Ermera": {
      "plane": [],
      "train": [],
      "bus": [
        {
          "code": "OSM:5377954221",
          "name": "Ermera",
          "lat": -8.7514527,
          "lng": 125.3968749
        }
      ]
    },
    "Viqueque": {
      "plane": [],
      "train": [],
      "bus": []
    },
    "Likisá": {
      "plane": [],
      "train": [],
      "bus": []
    },
    "Ainaro": {
      "plane": [],
      "train": [],
      "bus": []
    },
    "Manufahi": {
      "plane": [],
      "train": [],
      "bus": []
    },
    "Lautém": {
      "plane": [],
      "train": [],
      "bus": []
    },
    "Aileu": {
      "plane": [],
      "train": [],
      "bus": [
        {
          "code": "OSM:5356211421",
          "name": "Tasi Tolu",
          "lat": -8.5555605,
          "lng": 125.5123335
        }
      ]
    },
    "Oé-Cusse Ambeno": {
      "plane": [],
      "train": [],
      "bus": []
    },
    "Kovalima": {
      "plane": [],
      "train": [],
      "bus": []
    }
  },
  "meta": {
    "source": {
      "airports": "OurAirports (airports.csv, filtered: scheduled_service=yes, civil)",
      "train": "OpenStreetMap (railway=station/public_transport=station train=yes)",
      "bus": "OpenStreetMap (amenity=bus_station/public_transport=station bus=yes)"
    },
    "generatedAt": "2025-09-02T08:47:01.435Z"
  }
}